respond/__init__.py
respond/json_response.py
respond-1.0.dist-info/LICENSE
respond-1.0.dist-info/METADATA
respond-1.0.dist-info/WHEEL
respond-1.0.dist-info/top_level.txt
respond-1.0.dist-info/RECORD
