Metadata-Version: 2.1
Name: respond
Version: 1.0
Summary: A lightweight and useful wrapper around Flask's make_response and jsonify
Home-page: https://github.com/Julian-Nash/respond
Author: Julian Nash
Author-email: julianjamesnash@gmail.com
License: UNKNOWN
Project-URL: Bug Tracker, https://github.com/Julian-Nash/respond
Project-URL: Documentation, https://github.com/Julian-Nash/respond
Project-URL: Source Code, https://github.com/Julian-Nash/respond
Keywords: flask http request parser json rest
Platform: UNKNOWN
Classifier: Intended Audience :: Developers
Classifier: License :: OSI Approved :: MIT License
Classifier: Programming Language :: Python :: 3.6
Classifier: Programming Language :: Python :: 3.7
Classifier: Programming Language :: Python :: 3.8
Requires-Dist: flask
